exrates/__init__.py
exrates/__main__.py
exrates/__version__.py
exrates-1.0.7.dist-info/entry_points.txt
exrates-1.0.7.dist-info/LICENSE
exrates-1.0.7.dist-info/WHEEL
exrates-1.0.7.dist-info/METADATA
exrates-1.0.7.dist-info/RECORD
