Metadata-Version: 2.1
Name: exrates
Version: 1.0.7
Summary: Exrates is a simple Python application to get exchange rates
License: MIT
Author: Ömer Gök
Requires-Python: >=3.8,<4.0
Classifier: License :: OSI Approved :: MIT License
Classifier: Programming Language :: Python :: 3
Classifier: Programming Language :: Python :: 3.10
Classifier: Programming Language :: Python :: 3.8
Classifier: Programming Language :: Python :: 3.9
Requires-Dist: numpy (>=1.22.3,<2.0.0)
Requires-Dist: requests (>=2.27.1,<3.0.0)
